lalo/__init__.py
lalo/audio_manager.py
lalo/cli.py
lalo/config.py
lalo/epub_parser.py
lalo/exceptions.py
lalo/tts_engine.py
lalo/utils.py
lalo_tts-0.1.0.dist-info/licenses/LICENSE
lalo_tts-0.1.0.dist-info/METADATA
lalo_tts-0.1.0.dist-info/WHEEL
lalo_tts-0.1.0.dist-info/entry_points.txt
lalo_tts-0.1.0.dist-info/top_level.txt
lalo_tts-0.1.0.dist-info/RECORD
