Metadata-Version: 2.4
Name: lalo-tts
Version: 0.1.0
Summary: EPUB to audiobook converter using Qwen3-TTS
Author-email: Willian Paixao <willian@ufpa.br>
License-Expression: GPL-3.0-or-later
Project-URL: Homepage, https://github.com/willianpaixao/lalo
Project-URL: Documentation, https://github.com/willianpaixao/lalo#readme
Project-URL: Repository, https://github.com/willianpaixao/lalo
Project-URL: Bug Tracker, https://github.com/willianpaixao/lalo/issues
Project-URL: Changelog, https://github.com/willianpaixao/lalo/releases
Keywords: epub,tts,audiobook,qwen,text-to-speech
Classifier: Development Status :: 3 - Alpha
Classifier: Intended Audience :: End Users/Desktop
Classifier: Intended Audience :: Developers
Classifier: Operating System :: OS Independent
Classifier: Environment :: Console
Classifier: Environment :: GPU :: NVIDIA CUDA
Classifier: Natural Language :: English
Classifier: Programming Language :: Python :: 3
Classifier: Programming Language :: Python :: 3.12
Classifier: Programming Language :: Python :: 3 :: Only
Classifier: Topic :: Multimedia :: Sound/Audio :: Speech
Classifier: Topic :: Multimedia :: Sound/Audio :: Conversion
Classifier: Topic :: Text Processing
Classifier: Topic :: Utilities
Requires-Python: >=3.12
License-File: LICENSE
Requires-Dist: qwen-tts>=0.0.5
Requires-Dist: ebooklib>=0.18
Requires-Dist: beautifulsoup4>=4.12.0
Requires-Dist: lxml>=4.9.0
Requires-Dist: soundfile>=0.12.1
Requires-Dist: pydub>=0.25.1
Requires-Dist: click>=8.1.0
Requires-Dist: rich>=13.0.0
Requires-Dist: langdetect>=1.0.9
Requires-Dist: torch<3.0.0,>=2.0.0
Requires-Dist: mutagen>=1.47.0
Provides-Extra: dev
Requires-Dist: pytest>=7.0.0; extra == "dev"
Requires-Dist: pytest-cov>=4.0.0; extra == "dev"
Requires-Dist: ruff>=0.8.0; extra == "dev"
Requires-Dist: mypy>=1.0.0; extra == "dev"
Requires-Dist: pyright>=1.1.390; extra == "dev"
Requires-Dist: pre-commit>=4.0.0; extra == "dev"
Dynamic: license-file
